pushy/.DS_Store
pushy/__init__.py
pushy/__main__.py
pushy/config.ini
pushy/config.py
pushy/pushy.py
pushy/sdk.py
pushy/lib/api.py
pushy/lib/mqtt.py
pushy/util/config.py
pushy/util/localStorage.py
pushy_python-1.0.12.dist-info/LICENSE
pushy_python-1.0.12.dist-info/METADATA
pushy_python-1.0.12.dist-info/WHEEL
pushy_python-1.0.12.dist-info/top_level.txt
pushy_python-1.0.12.dist-info/RECORD
