Metadata-Version: 2.1
Name: pushy-python
Version: 1.0.12
Summary: The official Pushy SDK for Python apps.
Home-page: https://github.com/pushy/pushy-python
Author: Pushy
Author-email: support@pushy.me
License: Apache 2.0
Classifier: Programming Language :: Python :: 3
Classifier: Programming Language :: Python :: 3.7
License-File: LICENSE
Requires-Dist: paho-mqtt ==1.6.1
Requires-Dist: requests
Requires-Dist: pathlib
